Youtube_package/__init__.py
Youtube_package/embed.py
Youtube_package/metadata.py
Youtube_package/preview.py
Youtube_package/utils.py
youtube_package-0.2.0.dist-info/METADATA
youtube_package-0.2.0.dist-info/WHEEL
youtube_package-0.2.0.dist-info/top_level.txt
youtube_package-0.2.0.dist-info/RECORD
