Metadata-Version: 2.4
Name: Youtube_package
Version: 0.2.0
Summary: A Jupyter-friendly YouTube embedding and metadata tool
Author: abhishek chaudhary
Classifier: Programming Language :: Python :: 3
Classifier: Operating System :: OS Independent
Requires-Python: >=3.6
Requires-Dist: requests
Requires-Dist: IPython
Requires-Dist: pytube
Dynamic: author
Dynamic: classifier
Dynamic: requires-dist
Dynamic: requires-python
Dynamic: summary
